setup.py
Pyforms_Lite.egg-info/PKG-INFO
Pyforms_Lite.egg-info/SOURCES.txt
Pyforms_Lite.egg-info/dependency_links.txt
Pyforms_Lite.egg-info/requires.txt
Pyforms_Lite.egg-info/top_level.txt
pyforms_lite/__init__.py
pyforms_lite/controls.py
pyforms_lite/dialogs.py
pyforms_lite/settings.py
pyforms_lite/gui/__init__.py
pyforms_lite/gui/appmanager.py
pyforms_lite/gui/basewidget.py
pyforms_lite/gui/settings.py
pyforms_lite/gui/controls/ControlBase.py
pyforms_lite/gui/controls/ControlBoundingSlider.py
pyforms_lite/gui/controls/ControlButton.py
pyforms_lite/gui/controls/ControlCheckBox.py
pyforms_lite/gui/controls/ControlCheckBoxList.py
pyforms_lite/gui/controls/ControlCombo.py
pyforms_lite/gui/controls/ControlDir.py
pyforms_lite/gui/controls/ControlDockWidget.py
pyforms_lite/gui/controls/ControlEmptyWidget.py
pyforms_lite/gui/controls/ControlFile.py
pyforms_lite/gui/controls/ControlFilesTree.py
pyforms_lite/gui/controls/ControlLabel.py
pyforms_lite/gui/controls/ControlList.py
pyforms_lite/gui/controls/ControlMdiArea.py
pyforms_lite/gui/controls/ControlNumber.py
pyforms_lite/gui/controls/ControlProgress.py
pyforms_lite/gui/controls/ControlSlider.py
pyforms_lite/gui/controls/ControlTableView.py
pyforms_lite/gui/controls/ControlText.py
pyforms_lite/gui/controls/ControlTextArea.py
pyforms_lite/gui/controls/ControlToolBox.py
pyforms_lite/gui/controls/ControlToolButton.py
pyforms_lite/gui/controls/ControlTree.py
pyforms_lite/gui/controls/ControlTreeView.py
pyforms_lite/gui/controls/ControlWeb.py
pyforms_lite/gui/controls/__init__.py
pyforms_lite/gui/controls/button.ui
pyforms_lite/gui/controls/checkbox.ui
pyforms_lite/gui/controls/fileInput.ui
pyforms_lite/gui/controls/image.ui
pyforms_lite/gui/controls/label.ui
pyforms_lite/gui/controls/list.ui
pyforms_lite/gui/controls/number.ui
pyforms_lite/gui/controls/progressInput.ui
pyforms_lite/gui/controls/sliderInput.ui
pyforms_lite/gui/controls/table-view.ui
pyforms_lite/gui/controls/textArea.ui
pyforms_lite/gui/controls/textInput.ui
pyforms_lite/gui/controls/tree.ui
pyforms_lite/gui/controls/uipics/add.png
pyforms_lite/gui/controls/uipics/film.png
pyforms_lite/gui/controls/uipics/film_edit.png
