Metadata-Version: 1.0
Name: Pyforms-Lite
Version: 3.0.4
Summary: Pyforms-Lite is a Python 2.7 and 3.5 framework to develop GUI applications based on PyQt
Home-page: https://github.com/NikhilNarayana/pyforms-lite
Author: Nikhil Narayana
Author-email: nikhil.narayana@live.com
License: MIT
Platform: UNKNOWN
